Workbook

Sheet bike_sales_UNCLEAN
A1: Sales_Order # | B1: Date_Combined | C1: Customer_Age | D1: Age_Group | E1: Customer_Gender | F1: Country | G1: State | H1: Product_Category | I1: Sub_Category | J1: Product_Description | K1: Order_Quantity | L1: Unit_Cost | M1: Unit_Price | N1: Profit | O1: Cost | P1: Revenue
A2: 261762 | B2: 44549 | C2: 63 | E2: Female | F2: Australia | G2: Queensland | H2: BIKES | I2: MOUNTAIN BIKES | J2: Mountain-200 Black, 46 | K2: 4 | L2: 1252 | M2: 2295 | N2: 4172 | O2: 5008 | P2: 9180
A3: 261716 | B3: 44538 | C3: 35 | D3: ADULTS (35-64) | E3: Female | F3: United States | G3: CALIFORNIA | H3: BIKES | I3: MOUNTAIN BIKES | J3: Mountain-500 Black, 42 | L3: 295 | M3: 540 | N3: 245 | O3: 0 | P3: 0
A4: 261766 | B4: 44550 | C4: 33 | D4: young adults (25-34) | E4: Female | F4: AUSTRALIA | G4: VICTORIA | H4: BIKES | I4: MOUNTAIN BIKES | J4: Mountain-100 Black, 38 | K4: 4 | L4: 1898 | M4: 3375 | N4: 5908 | O4: 7592 | P4: 13500
A5: 261767 | B5: 44550 | D5: ADULTS (35-64) | E5: Male | F5: Australia | G5: QUEENSLAND | H5: Bikes | I5: Mountain Bikes | J5: Mountain-200 Black, 46 | K5: 4 | L5: 1252 | M5: 2295 | N5: 4172 | O5: 5008 | P5: 9180
A6: 261695 | B6: 44531 | C6: 39 | D6: adults (35-64) | E6: Female | F6: United States | G6: California | H6: bikes | I6: Mountain Bikes | J6: Mountain-200 Black, 46 | K6: 4 | L6: 1252 | M6: 2295 | N6: 4172 | O6: 5008 | P6: 9180
A7: 261720 | B7: 44540 | E7: Male | F7: Australia | G7: NEW SOUTH WALES | H7: bikes | I7: Mountain Bikes | J7: Mountain-200 Black, 42 | K7: 2 | L7: 1252 | M7: 2295 | N7: 2086 | O7: 2504 | P7: 4590
A8: 261734 | B8: #NAME? | C8: 38 | E8: Female | F8: United States | G8: washington | H8: BIKES | I8: Mountain Bikes | J8: Mountain-200 Silver, 42 | K8: 1 | L8: 1266 | M8: 2320 | N8: 1054 | O8: 1266 | P8: 2320
A9: 261736 | B9: 44543 | C9: 40 | D9: ADULTS (35-64) | E9: Female | F9: United States | G9: California | H9: BIKES | I9: MOUNTAIN BIKES | J9: Mountain-500 Silver, 40 | K9: 1 | L9: 308 | M9: 565 | N9: 257 | O9: 308 | P9: 565
A10: 261704 | B10: #NAME? | C10: 42 | D10: Adults (35-64) | E10: Male | F10: germany | G10: NORDRHEIN-WESTFALEN | H10: bikes | I10: MOUNTAIN BIKES | J10: Mountain-200 Black, 38 | K10: 4 | L10: 1252 | M10: 2295 | N10: 4172 | O10: 5008 | P10: 9180
A11: 261739 | B11: 44544 | C11: 30 | D11: YOUNG ADULTS (25-34) | E11: Female | F11: United States | G11: WASHINGTON | H11: bikes | I11: MOUNTAIN BIKES | J11: Mountain-200 Silver, 38 | K11: 2 | L11: 1266 | M11: 2320 | N11: 2108 | O11: 2532 | P11: 4640
A12: 261778 | B12: #NAME? | C12: 41 | D12: adults (35-64) | E12: Male | F12: Germany | G12: Hessen | H12: BIKES | I12: Mountain Bikes | J12: Mountain-200 Silver, 38 | K12: 1 | L12: 1266 | M12: 2320 | N12: 1054 | O12: 1266 | P12: 2320
A13: 261749 | B13: 44548 | C13: 35 | D13: Adults (35-64) | E13: Female | F13: AUSTRALIA | G13: NEW SOUTH WALES | H13: bikes | I13: Mountain Bikes | J13: Mountain-500 Silver, 42 | K13: 4 | L13: 308 | M13: 565 | N13: 1028 | O13: 1232 | P13: 2260
A14: 261775 | B14: 44552 | C14: 19 | D14: youth (<25) | E14: Female | F14: AUSTRALIA | G14: NEW SOUTH WALES | H14: BIKES | I14: mountain bikes | J14: Mountain-500 Silver, 42 | K14: 1 | L14: 308 | M14: 565 | N14: 257 | O14: 308 | P14: 565
A15: 261741 | B15: 44544 | C15: 32 | D15: Young Adults (25-34) | E15: Female | F15: australia | G15: victoria | H15: BIKES | I15: mountain bikes | J15: Mountain-400-W Silver, 46 | K15: 1 | L15: 420 | M15: 769 | N15: 349 | O15: 420 | P15: 769
A16: 261706 | B16: 44535 | D16: ADULTS (35-64) | E16: Female | F16: United States | G16: California | H16: BIKES | I16: Mountain Bikes | J16: Mountain-200 Black, 46 | K16: 1 | L16: 1252 | M16: 2295 | N16: 1043 | O16: 1252 | P16: 2295
A17: 261699 | B17: 44533 | C17: 37 | E17: Female | F17: United States | G17: California | H17: BIKES | I17: Mountain Bikes | J17: Mountain-200 Black, 46 | L17: 0 | M17: 2295 | N17: 2086 | O17: 0 | P17: 4590
A18: 261712 | B18: 44537 | C18: 38 | D18: ADULTS (35-64) | E18: Male | F18: United States | G18: CALIFORNIA | H18: bikes | I18: MOUNTAIN BIKES | J18: Mountain-200 Silver, 42 | K18: 2 | L18: 1266 | M18: 2320 | N18: 2108 | O18: 2532 | P18: 4640
A19: 261722 | B19: 44540 | C19: 34 | D19: YOUNG ADULTS (25-34) | E19: Male | F19: United States | G19: california | H19: bikes | I19: mountain bikes | J19: Mountain-500 Black, 40 | K19: 1 | L19: 295 | M19: 540 | N19: 245 | O19: 295 | P19: 540
A20: 261733 | B20: 44542 | C20: 35 | D20: Adults (35-64) | E20: Female | F20: Australia | G20: Victoria | H20: Bikes | I20: MOUNTAIN BIKES | J20: Mountain-200 Silver, 42 | L20: 1266 | M20: 2320 | N20: 1054 | O20: 1266 | P20: 2320
A21: 261760 | B21: 44549 | C21: 37 | D21: ADULTS (35-64) | E21: Male | F21: United States | G21: OREGON | H21: bikes | I21: Mountain Bikes | J21: Mountain-200 Black, 38 | K21: 4 | L21: 1252 | M21: 2295 | N21: 4172 | O21: 5008 | P21: 9180
A22: 261709 | B22: 44536 | C22: 36 | E22: Male | F22: Australia | G22: new south wales | H22: Bikes | I22: Mountain Bikes | J22: Mountain-200 Black, 42 | K22: 1 | L22: 1252 | M22: 2295 | N22: 1043 | O22: 1252 | P22: 2295
A23: 261772 | B23: 44551 | C23: 23 | D23: youth (<25) | E23: Male | F23: UNITED KINGDOM | G23: england | H23: bikes | I23: mountain bikes | J23: Mountain-400-W Silver, 46 | K23: 2 | L23: 420 | M23: 769 | N23: 698 | O23: 840 | P23: 1538
A24: 261773 | B24: 44552 | C24: 30 | D24: Young Adults (25-34) | E24: Female | F24: United States | G24: Washington | H24: Bikes | I24: Mountain Bikes | J24: Mountain-200 Silver, 38 | K24: 3 | L24: 1266 | M24: 2320 | N24: 3162 | O24: 3798 | P24: 6960
A25: 261724 | B25: 44540 | C25: 38 | D25: ADULTS (35-64) | E25: Male | F25: australia | G25: New South Wales | H25: bikes | I25: mountain bikes | J25: Mountain-200 Black, 38 | K25: 1 | L25: 1252 | M25: 2295 | N25: 1043 | O25: 1252 | P25: 2295
A26: 261727 | B26: 44541 | C26: 27 | D26: Young Adults (25-34) | E26: Male | F26: canada | G26: British Columbia | H26: BIKES | I26: mountain bikes | J26: Mountain-200 Black, 46 | K26: 1 | L26: 1252 | M26: 2295 | N26: 1043 | O26: 1252 | P26: 2295
A27: 261705 | B27: 44535 | C27: 35 | D27: ADULTS (35-64) | E27: Female | F27: Australia | G27: Queensland | H27: Bikes | I27: mountain bikes | J27: Mountain-200 Silver, 38 | K27: 1 | L27: 1266 | M27: 2320 | N27: 1054 | O27: 1266 | P27: 2320
A28: 261738 | B28: 44543 | C28: 49 | D28: adults (35-64) | E28: Male | F28: united kingdom | G28: England | H28: bikes | I28: MOUNTAIN BIKES | J28: Mountain-200 Black, 38 | K28: 1 | L28: 1252 | M28: 2295 | N28: 1043 | O28: 1252 | P28: 2295
A29: 261743 | B29: 16--2021 | C29: 33 | E29: Female | F29: AUSTRALIA | G29: New South Wales | H29: BIKES | I29: mountain bikes | J29: Mountain-200 Black, 38 | K29: 2 | L29: 1252 | M29: 2295 | N29: 2086 | O29: 2504 | P29: 4590
A30: 261725 | B30: 44541 | C30: 24 | D30: Youth (<25) | E30: Female | F30: france | G30: SEINE (PARIS) | H30: bikes | I30: MOUNTAIN BIKES | J30: Mountain-200 Black, 38 | K30: 3 | L30: 1252 | M30: 2295 | N30: 3129 | O30: 3756 | P30: 6885
A31: 261761 | B31: #NAME? | C31: 39 | D31: ADULTS (35-64) | E31: Female | F31: United States | G31: CALIFORNIA | H31: BIKES | I31: Mountain Bikes | J31: Mountain-200 Black, 46 | K31: 4 | L31: 1252 | M31: 2295 | N31: 4172 | O31: 5008 | P31: 9180
A32: 261703 | B32: 44535 | C32: 39 | D32: adults (35-64) | E32: Female | F32: United States | G32: california | H32: bikes | I32: Mountain Bikes | J32: Mountain-200 Black, 46 | K32: 4 | L32: 1252 | M32: 2295 | N32: 4172 | O32: 5008 | P32: 9180
A33: 261757 | B33: 44549 | C33: 19 | D33: youth (<25) | E33: Female | F33: australia | G33: VICTORIA | H33: bikes | I33: mountain bikes | J33: Mountain-500 Black, 44 | K33: 4 | L33: 295 | M33: 540 | N33: 980 | O33: 1180 | P33: 2160
A34: 261700 | B34: #NAME? | C34: 24 | D34: Youth (<25) | E34: Female | F34: United Kingdom | G34: England | H34: Bikes | I34: MOUNTAIN BIKES | J34: Mountain-200 Black, 38 | K34: 1 | L34: 1252 | M34: 2295 | N34: 1043 | O34: 1252 | P34: 2295
A35: 261763 | B35: 44549 | D35: YOUTH (<25) | E35: Male | F35: AUSTRALIA | G35: South Australia | H35: Bikes | I35: mountain bikes | J35: Mountain-500 Black, 40 | K35: 2 | L35: 295 | M35: 540 | N35: 490 | O35: 590 | P35: 1080
A36: 261764 | B36: 44549 | C36: 56 | D36: adults (35-64) | E36: Female | F36: Germany | G36: HESSEN | H36: Bikes | I36: mountain bikes | J36: Mountain-200 Black, 46 | K36: 2 | L36: 1252 | M36: 2295 | N36: 2086 | O36: 2504 | P36: 4590
A37: 261729 | B37: 44541 | C37: 38 | D37: adults (35-64) | E37: Female | F37: United States | G37: California | H37: Bikes | I37: Mountain Bikes | J37: Mountain-200 Silver, 38 | K37: 1 | L37: 1266 | M37: 2320 | N37: 1054 | O37: 1266 | P37: 2320
A38: 261710 | B38: 44536 | C38: 47 | D38: ADULTS (35-64) | E38: Male | F38: united kingdom | G38: england | H38: BIKES | I38: mountain bikes | J38: Mountain-200 Silver, 38 | K38: 1 | L38: 1266 | M38: 2320 | N38: 1054 | O38: 1266 | P38: 2320
A39: 261770 | B39: 44550 | C39: 35 | D39: Adults (35-64) | E39: Male | F39: Australia | G39: Victoria | H39: BIKES | I39: Mountain Bikes | J39: Mountain-200 Silver, 38 | K39: 1 | L39: 1266 | M39: 2320 | N39: 1054 | O39: 1266 | P39: 2320
A40: 261728 | B40: 44541 | C40: 37 | D40: ADULTS (35-64) | E40: Male | F40: United States | G40: california | H40: bikes | I40: Mountain Bikes | J40: Mountain-400-W Silver, 46 | K40: 1 | L40: 420 | M40: 769 | N40: 349 | O40: 420 | P40: 769
A41: 261701 | B41: 44533 | C41: 37 | D41: Adults (35-64) | E41: Male | F41: United States | G41: WASHINGTON | H41: bikes | I41: Mountain Bikes | J41: Mountain-200 Black, 46 | K41: 1 | L41: 1252 | M41: 2295 | N41: 1043 | O41: 1252 | P41: 2295
A42: 261747 | B42: 44547 | C42: 31 | D42: young adults (25-34) | E42: Male | F42: AUSTRALIA | G42: New South Wales | H42: bikes | I42: Mountain Bikes | J42: Mountain-400-W Silver, 42 | K42: 1 | L42: 420 | M42: 769 | N42: 349 | O42: 420 | P42: 769
A43: 261721 | B43: 44540 | C43: 26 | D43: young adults (25-34) | E43: Male | F43: united kingdom | G43: England | H43: BIKES | I43: Mountain Bikes | J43: Mountain-200 Black, 38 | K43: 1 | L43: 1252 | M43: 2295 | N43: 1043 | O43: 1252 | P43: 2295
A44: 261713 | B44: #NAME? | C44: 19 | D44: youth (<25) | E44: Female | F44: AUSTRALIA | G44: new south wales | H44: Bikes | I44: Mountain Bikes | J44: Mountain-500 Silver, 42 | K44: 4 | L44: 308 | M44: 565 | N44: 1028 | O44: 1232 | P44: 2260
A45: 261771 | B45: 44551 | C45: 26 | D45: Young Adults (25-34) | E45: Male | F45: france | G45: SOMME | H45: Bikes | I45: Mountain Bikes | J45: Mountain-200 Silver, 38 | K45: 3 | L45: 1266 | M45: 2320 | N45: 3162 | O45: 3798 | P45: 6960
A46: 261719 | B46: 10--2021 | C46: 34 | D46: YOUNG ADULTS (25-34) | E46: Female | F46: United States | G46: CALIFORNIA | H46: Bikes | I46: MOUNTAIN BIKES | J46: Mountain-200 Black, 42 | K46: 2 | L46: 1252 | M46: 2295 | N46: 2086 | O46: 2504 | P46: 4590
A47: 261763 | B47: 44549 | C47: 18 | D47: YOUTH (<25) | E47: Male | F47: AUSTRALIA | G47: South Australia | H47: Bikes | I47: mountain bikes | J47: Mountain-500 Black, 40 | K47: 2 | L47: 295 | M47: 540 | N47: 490 | O47: 590 | P47: 1080
A48: 261707 | B48: 44536 | C48: 23 | D48: YOUTH (<25) | E48: Male | F48: United Kingdom | G48: ENGLAND | H48: Bikes | I48: Mountain Bikes | J48: Mountain-400-W Silver, 46 | K48: 3 | L48: 420 | M48: 769 | N48: 1047 | O48: 1260 | P48: 2307
A49: 261718 | B49: 44539 | C49: 41 | E49: Female | F49: GERMANY | G49: Hamburg | H49: BIKES | I49: mountain bikes | J49: Mountain-200 Silver, 42 | L49: 1266 | M49: 2320 | N49: 1054 | O49: 1266 | P49: 2320
A50: 261698 | B50: 44532 | C50: 31 | D50: young adults (25-34) | E50: Female | F50: AUSTRALIA | G50: new south wales | H50: BIKES | I50: MOUNTAIN BIKES | J50: Mountain-400-W Silver, 42 | K50: 1 | L50: 420 | M50: 769 | N50: 349 | O50: 420 | P50: 769
A51: 261711 | B51: 7-Decmber-2021 | C51: 30 | E51: Male | F51: United States | G51: CALIFORNIA | H51: BIKES | I51: mountain bikes | J51: Mountain-400-W Silver, 38 | K51: 4 | L51: 420 | M51: 769 | N51: 1396 | O51: 1680 | P51: 3076
A52: 261732 | B52: 44542 | E52: Male | F52: Australia | G52: New South Wales | H52: Bikes | I52: Mountain Bikes | J52: Mountain-200 Black, 38 | K52: 2 | L52: 1252 | M52: 2295 | N52: 2086 | O52: 2504 | P52: 4590
A53: 261702 | B53: 44534 | C53: 31 | D53: Young Adults (25-34) | E53: Female | F53: australia | G53: NEW SOUTH WALES | H53: bikes | I53: MOUNTAIN BIKES | J53: Mountain-400-W Silver, 42 | K53: 4 | L53: 420 | M53: 0 | N53: 1396 | O53: 1680 | P53: 0
A54: 261779 | B54: 44553 | C54: 30 | D54: YOUNG ADULTS (25-34) | E54: Female | F54: United States | G54: Oregon | H54: BIKES | I54: mountain bikes | J54: Mountain-200 Silver, 42 | K54: 1 | L54: 1266 | M54: 2320 | N54: 1054 | O54: 1266 | P54: 2320
A55: 261701 | B55: 44533 | D55: adults (35-64) | E55: Male | F55: United States | G55: Washington | H55: bikes | I55: Mountain Bikes | J55: Mountain-200 Black, 46 | K55: 1 | L55: 1252 | M55: 2295 | N55: 1043 | O55: 1252 | P55: 2295
A56: 261756 | B56: 44549 | C56: 17 | D56: youth (<25) | E56: Male | F56: france | G56: Nord | H56: Bikes | I56: MOUNTAIN BIKES | J56: Mountain-200 Silver, 46 | L56: 1266 | M56: 2320 | N56: 4216 | O56: 5064 | P56: 9280
A57: 261730 | B57: 44542 | C57: 36 | D57: Adults (35-64) | E57: Female | F57: AUSTRALIA | G57: NEW SOUTH WALES | H57: BIKES | I57: MOUNTAIN BIKES | J57: Mountain-200 Silver, 42 | K57: 4 | L57: 1266 | M57: 2320 | N57: 4216 | O57: 5064 | P57: 9280
A58: 261777 | B58: 44552 | C58: 27 | D58: YOUNG ADULTS (25-34) | E58: Female | F58: CANADA | G58: BRITISH COLUMBIA | H58: Bikes | I58: MOUNTAIN BIKES | J58: Mountain-200 Black, 46 | K58: 1 | L58: 1252 | M58: 2295 | N58: 1043 | O58: 1252 | P58: 2295
A59: 261750 | B59: 44548 | C59: 38 | D59: ADULTS (35-64) | E59: Female | F59: Germany | G59: NORDRHEIN-WESTFALEN | H59: bikes | I59: MOUNTAIN BIKES | J59: Mountain-200 Silver, 46 | K59: 4 | L59: 1266 | M59: 2320 | N59: 4216 | O59: 5064 | P59: 9280
A60: 261770 | B60: #NAME? | C60: 35 | D60: Adults (35-64) | E60: Male | F60: Australia | G60: Victoria | H60: BIKES | I60: Mountain Bikes | J60: Mountain-200 Silver, 38 | K60: 1 | L60: 1266 | M60: 2320 | N60: 1054 | O60: 1266 | P60: 2320
A61: 261748 | B61: 44547 | C61: 42 | D61: ADULTS (35-64) | E61: Female | F61: GERMANY | G61: nordrhein-westfalen | H61: bikes | I61: Mountain Bikes | J61: Mountain-200 Silver, 46 | K61: 1 | L61: 1266 | M61: 2320 | N61: 1054 | O61: 1266 | P61: 2320
A62: 261737 | B62: 44543 | C62: 44 | D62: ADULTS (35-64) | E62: Female | F62: United Kingdom | G62: England | H62: BIKES | I62: mountain bikes | J62: Mountain-200 Black, 38 | K62: 1 | L62: 1252 | M62: 2295 | N62: 1043 | O62: 1252 | P62: 2295
A63: 261744 | B63: 44546 | C63: 38 | D63: Adults (35-64) | E63: Male | F63: Australia | G63: New South Wales | H63: BIKES | I63: Mountain Bikes | J63: Mountain-200 Black, 38 | K63: 2 | L63: 1252 | M63: 2295 | N63: 2086 | O63: 2504 | P63: 4590
A64: 261758 | B64: 44549 | C64: 25 | E64: Male | F64: France | G64: Seine (Paris) | H64: BIKES | I64: MOUNTAIN BIKES | J64: Mountain-200 Black, 38 | K64: 4 | L64: 1252 | M64: 2295 | N64: 4172 | O64: 5008 | P64: 9180
A65: 261740 | B65: 44544 | C65: 32 | D65: YOUNG ADULTS (25-34) | E65: Male | F65: United States | G65: California | H65: bikes | I65: mountain bikes | J65: Mountain-200 Black, 46 | K65: 1 | L65: 1252 | M65: 2295 | N65: 1043 | O65: 1252 | P65: 2295
A66: 261759 | B66: 44549 | C66: 35 | D66: ADULTS (35-64) | E66: Female | F66: United States | G66: OREGON | H66: BIKES | I66: MOUNTAIN BIKES | J66: Mountain-100 Black, 48 | K66: 4 | L66: 1898 | M66: 3375 | N66: 5908 | O66: 7592 | P66: 13500
A67: 261755 | B67: 44548 | C67: 36 | D67: ADULTS (35-64) | E67: Male | F67: United States | G67: Washington | H67: Bikes | I67: MOUNTAIN BIKES | J67: Mountain-200 Silver, 38 | K67: 1 | L67: 1266 | M67: 2320 | N67: 1054 | O67: 1266 | P67: 2320
A68: 261704 | B68: #NAME? | C68: 42 | D68: Adults (35-64) | E68: Male | F68: germany | G68: NORDRHEIN-WESTFALEN | H68: bikes | I68: MOUNTAIN BIKES | J68: Mountain-200 Black, 38 | K68: 4 | L68: 1252 | M68: 2295 | N68: 4172 | O68: 5008 | P68: 9180
A69: 261769 | B69: 44550 | C69: 35 | D69: adults (35-64) | E69: Female | F69: australia | G69: QUEENSLAND | H69: BIKES | I69: MOUNTAIN BIKES | J69: Mountain-200 Silver, 38 | K69: 1 | L69: 1266 | M69: 2320 | N69: 1054 | O69: 1266 | P69: 2320
A70: 261735 | B70: #NAME? | C70: 32 | D70: YOUNG ADULTS (25-34) | E70: Female | F70: australia | G70: QUEENSLAND | H70: BIKES | I70: mountain bikes | J70: Mountain-200 Silver, 42 | K70: 3 | L70: 1266 | M70: 2320 | N70: 3162 | O70: 3798 | P70: 6960
A71: 261752 | B71: 44548 | C71: 26 | D71: YOUNG ADULTS (25-34) | E71: Female | F71: United Kingdom | G71: ENGLAND | H71: Bikes | I71: Mountain Bikes | J71: Mountain-400-W Silver, 42 | K71: 3 | L71: 420 | M71: 769 | N71: 1047 | O71: 1260 | P71: 2307
A72: 261742 | B72: 44545 | C72: 29 | D72: young adults (25-34) | E72: Female | F72: United States | G72: california | H72: bikes | I72: MOUNTAIN BIKES | J72: Mountain-200 Silver, 42 | K72: 1 | L72: 1266 | M72: 2320 | N72: 1054 | O72: 1266 | P72: 2320
A73: 261782 | B73: 44554 | C73: 38 | E73: Male | F73: AUSTRALIA | G73: QUEENSLAND | H73: BIKES | I73: MOUNTAIN BIKES | J73: Mountain-200 Black, 42 | K73: 4 | L73: 1252 | M73: 2295 | N73: 4172 | O73: 5008 | P73: 9180
A74: 261751 | B74: #NAME? | C74: 24 | D74: youth (<25) | E74: Female | F74: FRANCE | G74: SEINE SAINT DENIS | H74: bikes | I74: Mountain Bikes | J74: Mountain-200 Silver, 38 | K74: 3 | L74: 1266 | M74: 2320 | N74: 3162 | O74: 3798 | P74: 6960
A75: 261726 | B75: 44541 | D75: ADULTS (35-64) | E75: Female | F75: Australia | G75: NEW SOUTH WALES | H75: BIKES | I75: MOUNTAIN BIKES | J75: Mountain-400-W Silver, 38 | K75: 2 | L75: 420 | M75: 769 | N75: 698 | O75: 840 | P75: 1538
A76: 261758 | B76: 44549 | C76: 25 | D76: young adults (25-34) | E76: Male | F76: France | G76: Seine (Paris) | H76: BIKES | I76: MOUNTAIN BIKES | J76: Mountain-200 Black, 38 | K76: 4 | L76: 1252 | M76: 2295 | N76: 4172 | O76: 5008 | P76: 9180
A77: 261753 | B77: 44548 | C77: 39 | D77: adults (35-64) | E77: Male | F77: United States | G77: california | H77: Bikes | I77: mountain bikes | J77: Mountain-200 Black, 42 | K77: 3 | L77: 1252 | M77: 2295 | N77: 3129 | O77: 3756 | P77: 6885
A78: 261757 | B78: 19--2021 | D78: youth (<25) | E78: Female | F78: australia | G78: VICTORIA | H78: bikes | I78: mountain bikes | J78: Mountain-500 Black, 44 | K78: 4 | L78: 295 | M78: 540 | N78: 980 | O78: 1180 | P78: 2160
A79: 261774 | B79: #NAME? | C79: 41 | D79: Adults (35-64) | E79: Male | F79: United States | G79: california | H79: Bikes | I79: mountain bikes | J79: Mountain-200 Black, 42 | K79: 3 | L79: 1252 | M79: 2295 | N79: 3129 | O79: 3756 | P79: 6885
A80: 261731 | B80: 12--2021 | C80: 37 | D80: adults (35-64) | E80: Male | F80: United States | G80: california | H80: BIKES | I80: MOUNTAIN BIKES | J80: Mountain-400-W Silver, 46 | K80: 4 | L80: 420 | M80: 769 | N80: 1396 | O80: 1680 | P80: 3076
A81: 261723 | B81: 44540 | C81: 34 | D81: young adults (25-34) | E81: Female | F81: United States | G81: WASHINGTON | H81: BIKES | I81: mountain bikes | J81: Mountain-100 Silver, 44 | K81: 1 | L81: 1912 | M81: 3400 | N81: 1488 | O81: 1912 | P81: 3400
A82: 261695 | B82: 44531 | C82: 44 | D82: ADULTS (35-64) | E82: Male | F82: United Kingdom | G82: ENGLAND | H82: bikes | I82: MOUNTAIN BIKES | J82: Mountain-200 Silver, 42 | K82: 1 | L82: 1266 | M82: 2320 | N82: 1054 | O82: 1266 | P82: 2320
A83: 261746 | B83: 44547 | C83: 37 | D83: ADULTS (35-64) | E83: Female | F83: United States | G83: washington | H83: BIKES | I83: mountain bikes | J83: Mountain-200 Silver, 38 | K83: 2 | L83: 1266 | M83: 2320 | N83: 2108 | O83: 2532 | P83: 4640
A84: 261715 | B84: 44538 | C84: 39 | D84: Adults (35-64) | E84: Female | F84: United States | G84: OREGON | H84: BIKES | I84: mountain bikes | K84: 2 | L84: 1252 | M84: 2295 | N84: 2086 | O84: 2504 | P84: 4590
A85: 261697 | B85: #NAME? | C85: 37 | D85: Adults (35-64) | E85: Male | F85: United States | G85: California | H85: BIKES | I85: mountain bikes | J85: Mountain-400-W Silver, 46 | K85: 2 | L85: 420 | M85: 769 | N85: 698 | O85: 840 | P85: 1538
A86: 261717 | B86: 44539 | C86: 33 | E86: Female | F86: AUSTRALIA | G86: VICTORIA | H86: BIKES | I86: mountain bikes | J86: Mountain-100 Black, 38 | K86: 2 | L86: 1898 | M86: 3375 | N86: 2954 | O86: 3796 | P86: 6750
A87: 261781 | B87: 44553 | C87: 35 | D87: adults (35-64) | E87: Female | F87: United States | G87: california | H87: Bikes | I87: MOUNTAIN BIKES | J87: Mountain-500 Black, 42 | K87: 1 | L87: 295 | M87: 540 | N87: 245 | O87: 295 | P87: 540
A88: 261768 | B88: 44550 | C88: 29 | E88: Male | F88: Canada | G88: british columbia | H88: bikes | I88: mountain bikes | J88: Mountain-500 Black, 52 | K88: 3 | L88: 295 | M88: 540 | N88: 735 | O88: 885 | P88: 1620
A89: 261780 | B89: 44553 | C89: 31 | D89: Young Adults (25-34) | E89: Female | F89: canada | G89: British Columbia | H89: BIKES | I89: mountain bikes | J89: Mountain-200 Black, 42 | K89: 1 | L89: 1252 | M89: 2295 | N89: 1043 | O89: 1252 | P89: 2295
A90: 261776 | B90: 44552 | C90: 25 | D90: YOUNG ADULTS (25-34) | E90: Male | F90: france | G90: Seine (Paris) | H90: BIKES | I90: MOUNTAIN BIKES | J90: Mountain-200 Black, 38 | K90: 1 | L90: 1252 | M90: 2295 | N90: 1043 | O90: 1252 | P90: 2295
A91: 261714 | B91: 44538 | C91: 30 | D91: Young Adults (25-34) | E91: Female | F91: canada | G91: british columbia | H91: bikes | I91: Mountain Bikes | J91: Mountain-200 Silver, 38 | K91: 4 | L91: 1266 | M91: 2320 | N91: 4216 | O91: 5064 | P91: 9280
A92: 261754 | B92: 18--2021 | C92: 26 | D92: YOUNG ADULTS (25-34) | E92: Male | F92: France | G92: SEINE (PARIS) | H92: Bikes | I92: Mountain Bikes | J92: Mountain-200 Black, 46 | K92: 1 | L92: 1252 | M92: 2295 | N92: 1043 | O92: 1252 | P92: 2295
A93: 261765 | B93: 44549 | C93: 39 | D93: adults (35-64) | E93: Female | F93: United States | G93: WASHINGTON | H93: Bikes | I93: Mountain Bikes | J93: Mountain-200 Silver, 38 | K93: 1 | L93: 1266 | M93: 2320 | N93: 1054 | O93: 1266 | P93: 2320
A94: 261708 | B94: 6--2021 | C94: 27 | E94: Male | F94: CANADA | G94: British Columbia | H94: Bikes | I94: Mountain Bikes | J94: Mountain-200 Black, 46 | K94: 1 | L94: 1252 | M94: 2295 | N94: 1043 | O94: 1252 | P94: 2295
A95: 261750 | B95: 44548 | C95: 38 | D95: ADULTS (35-64) | E95: Female | F95: Germany | G95: NORDRHEIN-WESTFALEN | H95: bikes | I95: MOUNTAIN BIKES | J95: Mountain-200 Silver, 46 | K95: 4 | L95: 1266 | M95: 2320 | N95: 4216 | O95: 5064 | P95: 9280
A96: 261745 | B96: 44546 | C96: 27 | D96: Young Adults (25-34) | E96: Female | F96: france | G96: seine et marne | H96: bikes | I96: Mountain Bikes | J96: Mountain-200 Silver, 46 | K96: 1 | L96: 1266 | M96: 2320 | N96: 1054 | O96: 1266 | P96: 2320

Sheet bike_sales_CLEAN 
A1: Sales_Order # | B1: Date_Combined | C1: Customer_Age | D1: Age_Group | E1: Customer_Gender | F1: Country | G1: States | H1: Product_Category | I1: Sub_Category | J1: Product_Description | K1: Order_Quantity | L1: Unit_Cost | M1: Unit_Price | N1: Profit | O1: Cost | P1: Revenue
A2: 261695 | B2: 44531 | C2: 39 | D2: Adults (35-64) | E2: Female | F2: United States | G2: California | H2: Bikes | I2: Mountain Bikes | J2: Mountain-200 Black, 46 | K2: 4 | L2: 1252 | M2: 2295 | N2: 4172 | O2: 5008 | P2: 9180
A3: 261696 | B3: 44531 | C3: 44 | D3: Adults (35-64) | E3: Male | F3: United Kingdom | G3: England | H3: Bikes | I3: Mountain Bikes | J3: Mountain-200 Silver, 42 | K3: 1 | L3: 1266 | M3: 2320 | N3: 1054 | O3: 1266 | P3: 2320
A4: 261697 | B4: 44532 | C4: 37 | D4: Adults (35-64) | E4: Male | F4: United States | G4: California | H4: Bikes | I4: Mountain Bikes | J4: Mountain-400-W Silver, 46 | K4: 2 | L4: 420 | M4: 769 | N4: 698 | O4: 840 | P4: 1538
A5: 261698 | B5: 44533 | C5: 31 | D5: Young Adults (25-34) | E5: Female | F5: Australia | G5: New South Wales | H5: Bikes | I5: Mountain Bikes | J5: Mountain-400-W Silver, 42 | K5: 1 | L5: 420 | M5: 769 | N5: 349 | O5: 420 | P5: 769
A6: 261699 | B6: 44533 | C6: 37 | D6: Adults (35-64) | E6: Female | F6: United States | G6: California | H6: Bikes | I6: Mountain Bikes | J6: Mountain-200 Black, 46 | K6: 0 | L6: 0 | M6: 2295 | N6: 2086 | O6: 0 | P6: 4590
A7: 261700 | B7: 44534 | C7: 24 | D7: Youth (<25) | E7: Female | F7: United Kingdom | G7: England | H7: Bikes | I7: Mountain Bikes | J7: Mountain-200 Black, 38 | K7: 1 | L7: 1252 | M7: 2295 | N7: 1043 | O7: 1252 | P7: 2295
A8: 261701 | B8: 44535 | C8: 37 | D8: Adults (35-64) | E8: Male | F8: United States | G8: Washington | H8: Bikes | I8: Mountain Bikes | J8: Mountain-200 Black, 46 | K8: 1 | L8: 1252 | M8: 2295 | N8: 1043 | O8: 1252 | P8: 2295
A9: 261702 | B9: 44535 | C9: 31 | D9: Young Adults (25-34) | E9: Female | F9: Australia | G9: New South Wales | H9: Bikes | I9: Mountain Bikes | J9: Mountain-400-W Silver, 42 | K9: 4 | L9: 420 | M9: 0 | N9: 1396 | O9: 1680 | P9: 0
A10: 261703 | B10: 44535 | C10: 39 | D10: Adults (35-64) | E10: Female | F10: United States | G10: California | H10: Bikes | I10: Mountain Bikes | J10: Mountain-200 Black, 46 | K10: 4 | L10: 1252 | M10: 2295 | N10: 4172 | O10: 5008 | P10: 9180
A11: 261704 | B11: 44536 | C11: 42 | D11: Adults (35-64) | E11: Male | F11: Germany | G11: Nordrhein-Westfalen | H11: Bikes | I11: Mountain Bikes | J11: Mountain-200 Black, 38 | K11: 4 | L11: 1252 | M11: 2295 | N11: 4172 | O11: 5008 | P11: 9180
A12: 261705 | B12: 44536 | C12: 35 | D12: Adults (35-64) | E12: Female | F12: Australia | G12: Queensland | H12: Bikes | I12: Mountain Bikes | J12: Mountain-200 Silver, 38 | K12: 1 | L12: 1266 | M12: 2320 | N12: 1054 | O12: 1266 | P12: 2320
A13: 261706 | B13: 44536 | C13: 0 | D13: Adults (35-64) | E13: Female | F13: United States | G13: California | H13: Bikes | I13: Mountain Bikes | J13: Mountain-200 Black, 46 | K13: 1 | L13: 1252 | M13: 2295 | N13: 1043 | O13: 1252 | P13: 2295
... A79: 261782 | B79: 0 | C79: 38 | D79: Adults (35-64) | E79: Male | F79: Australia | G79: Queensland | H79: Bikes | I79: Mountain Bikes | J79: Mountain-200 Black, 42 | K79: 4 | L79: 1252 | M79: 2295 | N79: 4172 | O79: 5008 | P79: 9180

Sheet Formula and Functions
A1: Vlookup Formula | K1: IFS FORMULA
A2: Sales_Order # | B2: Customer_Gender | C2: Country | D2: States | E2: Order_Quantity | F2: Unit_Cost | G2: Unit_Price | H2: Profit | I2: Cost | J2: Revenue | K2: Performance status
A3: 261698 | B3: =VLOOKUP($A3,'bike_sales_CLEAN '!A1:P79,5,FALSE) -> Female | C3: {=VLOOKUP($A3,'bike_sales_CLEAN '!$A$1:$P$79,{6,7,11,12,13,14,15,16},FALSE)} -> Australia | D3: New South Wales | E3: 1 | F3: 420 | G3: 769 | H3: 349 | I3: 420 | J3: 769 | K3: {=_xlfn.IFS(J3<1000,"LOW",J3<5000,"AVERAGE",J3<10000,"HIGH",J3>10000,"VERY HIGH")} -> LOW
A4: 261700 | B4: =VLOOKUP($A4,'bike_sales_CLEAN '!A2:P80,5,FALSE) -> Female | C4: {=VLOOKUP($A4,'bike_sales_CLEAN '!$A$1:$P$79,{6,7,11,12,13,14,15,16},FALSE)} -> United Kingdom | D4: England | E4: 1 | F4: 1252 | G4: 2295 | H4: 1043 | I4: 1252 | J4: 2295 | K4: {=_xlfn.IFS(J4<1000,"LOW",J4<5000,"AVERAGE",J4<10000,"HIGH",J4>10000,"VERY HIGH")} -> AVERAGE
A5: 261714 | B5: =VLOOKUP($A5,'bike_sales_CLEAN '!A3:P81,5,FALSE) -> Female | C5: {=VLOOKUP($A5,'bike_sales_CLEAN '!$A$1:$P$79,{6,7,11,12,13,14,15,16},FALSE)} -> Canada | D5: British Columbia | E5: 4 | F5: 1266 | G5: 2320 | H5: 4216 | I5: 5064 | J5: 9280 | K5: {=_xlfn.IFS(J5<1000,"LOW",J5<5000,"AVERAGE",J5<10000,"HIGH",J5>10000,"VERY HIGH")} -> HIGH
A6: 261720 | B6: =VLOOKUP($A6,'bike_sales_CLEAN '!A4:P82,5,FALSE) -> Male | C6: {=VLOOKUP($A6,'bike_sales_CLEAN '!$A$1:$P$79,{6,7,11,12,13,14,15,16},FALSE)} -> Australia | D6: New South Wales | E6: 2 | F6: 1252 | G6: 2295 | H6: 2086 | I6: 2504 | J6: 4590 | K6: {=_xlfn.IFS(J6<1000,"LOW",J6<5000,"AVERAGE",J6<10000,"HIGH",J6>10000,"VERY HIGH")} -> AVERAGE
A7: 261725 | B7: =VLOOKUP($A7,'bike_sales_CLEAN '!A5:P83,5,FALSE) -> Female | C7: {=VLOOKUP($A7,'bike_sales_CLEAN '!$A$1:$P$79,{6,7,11,12,13,14,15,16},FALSE)} -> France | D7: Seine (Paris) | E7: 3 | F7: 1252 | G7: 2295 | H7: 3129 | I7: 3756 | J7: 6885 | K7: {=_xlfn.IFS(J7<1000,"LOW",J7<5000,"AVERAGE",J7<10000,"HIGH",J7>10000,"VERY HIGH")} -> HIGH
A8: 261730 | B8: =VLOOKUP($A8,'bike_sales_CLEAN '!A6:P84,5,FALSE) -> Female | C8: {=VLOOKUP($A8,'bike_sales_CLEAN '!$A$1:$P$79,{6,7,11,12,13,14,15,16},FALSE)} -> Australia | D8: New South Wales | E8: 4 | F8: 1266 | G8: 2320 | H8: 4216 | I8: 5064 | J8: 9280 | K8: {=_xlfn.IFS(J8<1000,"LOW",J8<5000,"AVERAGE",J8<10000,"HIGH",J8>10000,"VERY HIGH")} -> HIGH
A9: 261733 | B9: =VLOOKUP($A9,'bike_sales_CLEAN '!A7:P85,5,FALSE) -> Female | C9: {=VLOOKUP($A9,'bike_sales_CLEAN '!$A$1:$P$79,{6,7,11,12,13,14,15,16},FALSE)} -> Australia | D9: Victoria | E9: 0 | F9: 1266 | G9: 2320 | H9: 1054 | I9: 1266 | J9: 2320 | K9: {=_xlfn.IFS(J9<1000,"LOW",J9<5000,"AVERAGE",J9<10000,"HIGH",J9>10000,"VERY HIGH")} -> AVERAGE
A10: 261740 | B10: =VLOOKUP($A10,'bike_sales_CLEAN '!A8:P86,5,FALSE) -> Male | C10: {=VLOOKUP($A10,'bike_sales_CLEAN '!$A$1:$P$79,{6,7,11,12,13,14,15,16},FALSE)} -> United States | D10: California | E10: 1 | F10: 1252 | G10: 2295 | H10: 1043 | I10: 1252 | J10: 2295 | K10: {=_xlfn.IFS(J10<1000,"LOW",J10<5000,"AVERAGE",J10<10000,"HIGH",J10>10000,"VERY HIGH")} -> AVERAGE
A11: 261766 | B11: =VLOOKUP($A11,'bike_sales_CLEAN '!A9:P87,5,FALSE) -> Female | C11: {=VLOOKUP($A11,'bike_sales_CLEAN '!$A$1:$P$79,{6,7,11,12,13,14,15,16},FALSE)} -> Australia | D11: Victoria | E11: 4 | F11: 1898 | G11: 3375 | H11: 5908 | I11: 7592 | J11: 13500 | K11: {=_xlfn.IFS(J11<1000,"LOW",J11<5000,"AVERAGE",J11<10000,"HIGH",J11>10000,"VERY HIGH")} -> VERY HIGH
A15: Xlookup Formula | K15: IF FORMULA
A16: Sales_Order # | B16: Customer_Gender | C16: Country | D16: States | E16: Order_Quantity | F16: Unit_Cost | G16: Unit_Price | H16: Profit | I16: Cost | J16: Revenue | K16: Profit Status
A17: 261695 | B17: =_xlfn.XLOOKUP($A17,'bike_sales_CLEAN '!A:A,'bike_sales_CLEAN '!E:E) -> Female | C17: =_xlfn.XLOOKUP($A17,'bike_sales_CLEAN '!A:A,'bike_sales_CLEAN '!F:F) -> United States | D17: =_xlfn.XLOOKUP($A17,'bike_sales_CLEAN '!A:A,'bike_sales_CLEAN '!G:G) -> California | E17: {=_xlfn.XLOOKUP($A17,'bike_sales_CLEAN '!$A:$A,'bike_sales_CLEAN '!$K:$P)} -> 4 | F17: 1252 | G17: 2295 | H17: 4172 | I17: 5008 | J17: 9180 | K17: =IF(H17>1000,"GOOD","NOT GOOD") -> GOOD
A18: 261699 | B18: =_xlfn.XLOOKUP($A18,'bike_sales_CLEAN '!A:A,'bike_sales_CLEAN '!E:E) -> Female | C18: =_xlfn.XLOOKUP($A18,'bike_sales_CLEAN '!A:A,'bike_sales_CLEAN '!F:F) -> United States | D18: =_xlfn.XLOOKUP($A18,'bike_sales_CLEAN '!A:A,'bike_sales_CLEAN '!G:G) -> California | E18: {=_xlfn.XLOOKUP($A18,'bike_sales_CLEAN '!$A:$A,'bike_sales_CLEAN '!$K:$P)} -> 0 | F18: 0 | G18: 2295 | H18: 2086 | I18: 0 | J18: 4590 | K18: =IF(H18>1000,"GOOD","NOT GOOD") -> GOOD
A19: 261705 | B19: =_xlfn.XLOOKUP($A19,'bike_sales_CLEAN '!A:A,'bike_sales_CLEAN '!E:E) -> Female | C19: =_xlfn.XLOOKUP($A19,'bike_sales_CLEAN '!A:A,'bike_sales_CLEAN '!F:F) -> Australia | D19: =_xlfn.XLOOKUP($A19,'bike_sales_CLEAN '!A:A,'bike_sales_CLEAN '!G:G) -> Queensland | E19: {=_xlfn.XLOOKUP($A19,'bike_sales_CLEAN '!$A:$A,'bike_sales_CLEAN '!$K:$P)} -> 1 | F19: 1266 | G19: 2320 | H19: 1054 | I19: 1266 | J19: 2320 | K19: =IF(H19>1000,"GOOD","NOT GOOD") -> GOOD
A20: 261711 | B20: =_xlfn.XLOOKUP($A20,'bike_sales_CLEAN '!A:A,'bike_sales_CLEAN '!E:E) -> Male | C20: =_xlfn.XLOOKUP($A20,'bike_sales_CLEAN '!A:A,'bike_sales_CLEAN '!F:F) -> United States | D20: =_xlfn.XLOOKUP($A20,'bike_sales_CLEAN '!A:A,'bike_sales_CLEAN '!G:G) -> California | E20: {=_xlfn.XLOOKUP($A20,'bike_sales_CLEAN '!$A:$A,'bike_sales_CLEAN '!$K:$P)} -> 4 | F20: 420 | G20: 769 | H20: 1396 | I20: 1680 | J20: 3076 | K20: =IF(H20>1000,"GOOD","NOT GOOD") -> GOOD
A21: 261719 | B21: =_xlfn.XLOOKUP($A21,'bike_sales_CLEAN '!A:A,'bike_sales_CLEAN '!E:E) -> Female | C21: =_xlfn.XLOOKUP($A21,'bike_sales_CLEAN '!A:A,'bike_sales_CLEAN '!F:F) -> United States | D21: =_xlfn.XLOOKUP($A21,'bike_sales_CLEAN '!A:A,'bike_sales_CLEAN '!G:G) -> California | E21: {=_xlfn.XLOOKUP($A21,'bike_sales_CLEAN '!$A:$A,'bike_sales_CLEAN '!$K:$P)} -> 2 | F21: 1252 | G21: 2295 | H21: 2086 | I21: 2504 | J21: 4590 | K21: =IF(H21>1000,"GOOD","NOT GOOD") -> GOOD
A22: 261750 | B22: =_xlfn.XLOOKUP($A22,'bike_sales_CLEAN '!A:A,'bike_sales_CLEAN '!E:E) -> Female | C22: =_xlfn.XLOOKUP($A22,'bike_sales_CLEAN '!A:A,'bike_sales_CLEAN '!F:F) -> Germany | D22: =_xlfn.XLOOKUP($A22,'bike_sales_CLEAN '!A:A,'bike_sales_CLEAN '!G:G) -> Nordrhein-Westfalen | E22: {=_xlfn.XLOOKUP($A22,'bike_sales_CLEAN '!$A:$A,'bike_sales_CLEAN '!$K:$P)} -> 4 | F22: 1266 | G22: 2320 | H22: 4216 | I22: 5064 | J22: 9280 | K22: =IF(H22>1000,"GOOD","NOT GOOD") -> GOOD
A23: 261755 | B23: =_xlfn.XLOOKUP($A23,'bike_sales_CLEAN '!A:A,'bike_sales_CLEAN '!E:E) -> Male | C23: =_xlfn.XLOOKUP($A23,'bike_sales_CLEAN '!A:A,'bike_sales_CLEAN '!F:F) -> United States | D23: =_xlfn.XLOOKUP($A23,'bike_sales_CLEAN '!A:A,'bike_sales_CLEAN '!G:G) -> Washington | E23: {=_xlfn.XLOOKUP($A23,'bike_sales_CLEAN '!$A:$A,'bike_sales_CLEAN '!$K:$P)} -> 1 | F23: 1266 | G23: 2320 | H23: 1054 | I23: 1266 | J23: 2320 | K23: =IF(H23>1000,"GOOD","NOT GOOD") -> GOOD
A24: 261761 | B24: =_xlfn.XLOOKUP($A24,'bike_sales_CLEAN '!A:A,'bike_sales_CLEAN '!E:E) -> Female | C24: =_xlfn.XLOOKUP($A24,'bike_sales_CLEAN '!A:A,'bike_sales_CLEAN '!F:F) -> United States | D24: =_xlfn.XLOOKUP($A24,'bike_sales_CLEAN '!A:A,'bike_sales_CLEAN '!G:G) -> California | E24: {=_xlfn.XLOOKUP($A24,'bike_sales_CLEAN '!$A:$A,'bike_sales_CLEAN '!$K:$P)} -> 4 | F24: 1252 | G24: 2295 | H24: 4172 | I24: 5008 | J24: 9180 | K24: =IF(H24>1000,"GOOD","NOT GOOD") -> GOOD
A25: 261763 | B25: =_xlfn.XLOOKUP($A25,'bike_sales_CLEAN '!A:A,'bike_sales_CLEAN '!E:E) -> Male | C25: =_xlfn.XLOOKUP($A25,'bike_sales_CLEAN '!A:A,'bike_sales_CLEAN '!F:F) -> Australia | D25: =_xlfn.XLOOKUP($A25,'bike_sales_CLEAN '!A:A,'bike_sales_CLEAN '!G:G) -> South Australia | E25: {=_xlfn.XLOOKUP($A25,'bike_sales_CLEAN '!$A:$A,'bike_sales_CLEAN '!$K:$P)} -> 2 | F25: 295 | G25: 540 | H25: 490 | I25: 590 | J25: 1080 | K25: =IF(H25>1000,"GOOD","NOT GOOD") -> NOT GOOD
A30: Filter Formula
E32: Select Country
E34: United States
A37: Sales_Order # | B37: Date_Combined | C37: Customer_Age | D37: Age_Group | E37: Customer_Gender | F37: Country | G37: States | H37: Product_Category | I37: Sub_Category | J37: Product_Description | K37: Order_Quantity | L37: Unit_Cost | M37: Unit_Price | N37: Profit | O37: Cost | P37: Revenue
A38: {=_xlfn._xlws.FILTER('bike_sales_CLEAN '!A1:P79,'bike_sales_CLEAN '!F1:F79='Formula and Functions'!E34)} -> 261695 | B38: 44531 | C38: 39 | D38: Adults (35-64) | E38: Female | F38: United States | G38: California | H38: Bikes | I38: Mountain Bikes | J38: Mountain-200 Black, 46 | K38: 4 | L38: 1252 | M38: 2295 | N38: 4172 | O38: 5008 | P38: 9180
A39: 261697 | B39: 44532 | C39: 37 | D39: Adults (35-64) | E39: Male | F39: United States | G39: California | H39: Bikes | I39: Mountain Bikes | J39: Mountain-400-W Silver, 46 | K39: 2 | L39: 420 | M39: 769 | N39: 698 | O39: 840 | P39: 1538
A40: 261699 | B40: 44533 | C40: 37 | D40: Adults (35-64) | E40: Female | F40: United States | G40: California | H40: Bikes | I40: Mountain Bikes | J40: Mountain-200 Black, 46 | K40: 0 | L40: 0 | M40: 2295 | N40: 2086 | O40: 0 | P40: 4590
A41: 261701 | B41: 44535 | C41: 37 | D41: Adults (35-64) | E41: Male | F41: United States | G41: Washington | H41: Bikes | I41: Mountain Bikes | J41: Mountain-200 Black, 46 | K41: 1 | L41: 1252 | M41: 2295 | N41: 1043 | O41: 1252 | P41: 2295
A42: 261703 | B42: 44535 | C42: 39 | D42: Adults (35-64) | E42: Female | F42: United States | G42: California | H42: Bikes | I42: Mountain Bikes | J42: Mountain-200 Black, 46 | K42: 4 | L42: 1252 | M42: 2295 | N42: 4172 | O42: 5008 | P42: 9180
A43: 261706 | B43: 44536 | C43: 0 | D43: Adults (35-64) | E43: Female | F43: United States | G43: California | H43: Bikes | I43: Mountain Bikes | J43: Mountain-200 Black, 46 | K43: 1 | L43: 1252 | M43: 2295 | N43: 1043 | O43: 1252 | P43: 2295
A44: 261711 | B44: 44539 | C44: 30 | D44: Null | E44: Male | F44: United States | G44: California | H44: Bikes | I44: Mountain Bikes | J44: Mountain-400-W Silver, 38 | K44: 4 | L44: 420 | M44: 769 | N44: 1396 | O44: 1680 | P44: 3076
A45: 261712 | B45: 44539 | C45: 38 | D45: Adults (35-64) | E45: Male | F45: United States | G45: California | H45: Bikes | I45: Mountain Bikes | J45: Mountain-200 Silver, 42 | K45: 2 | L45: 1266 | M45: 2320 | N45: 2108 | O45: 2532 | P45: 4640
A46: 261715 | B46: 44540 | C46: 39 | D46: Adults (35-64) | E46: Female | F46: United States | G46: Oregon | H46: Bikes | I46: Mountain Bikes | J46: Null | K46: 2 | L46: 1252 | M46: 2295 | N46: 2086 | O46: 2504 | P46: 4590
A47: 261716 | B47: 44540 | C47: 35 | D47: Adults (35-64) | E47: Female | F47: United States | G47: California | H47: Bikes | I47: Mountain Bikes | J47: Mountain-500 Black, 42 | K47: 0 | L47: 295 | M47: 540 | N47: 245 | O47: 0 | P47: 0
A48: 261719 | B48: 44541 | C48: 34 | D48: Young Adults (25-34) | E48: Female | F48: United States | G48: California | H48: Bikes | I48: Mountain Bikes | J48: Mountain-200 Black, 42 | K48: 2 | L48: 1252 | M48: 2295 | N48: 2086 | O48: 2504 | P48: 4590
A49: 261722 | B49: 44541 | C49: 34 | D49: Young Adults (25-34) | E49: Male | F49: United States | G49: California | H49: Bikes | I49: Mountain Bikes | J49: Mountain-500 Black, 40 | K49: 1 | L49: 295 | M49: 540 | N49: 245 | O49: 295 | P49: 540
A50: 261723 | B50: 44542 | C50: 34 | D50: Young Adults (25-34) | E50: Female | F50: United States | G50: Washington | H50: Bikes | I50: Mountain Bikes | J50: Mountain-100 Silver, 44 | K50: 1 | L50: 1912 | M50: 3400 | N50: 1488 | O50: 1912 | P50: 3400
... A65: 261765 | B65: 44553 | C65: 39 | D65: Adults (35-64) | E65: Female | F65: United States | G65: Washington | H65: Bikes | I65: Mountain Bikes | J65: Mountain-200 Silver, 38 | K65: 1 | L65: 1266 | M65: 2320 | N65: 1054 | O65: 1266 | P65: 2320

Sheet Pivot table
A3: country | B3: Sum of Revenue | C3: Sum of Cost | D3: Sum of Profit | E3: Sum of Unit_Price | F3: Sum of Unit_Cost
A4: Australia | B4: 107865 | C4: 60872 | D4: 50069 | E4: 46611 | F4: 25966
A5: Canada | B5: 15490 | C5: 8453 | D5: 7037 | E5: 7450 | F5: 4065
A6: France | B6: 43880 | C6: 23942 | D6: 19938 | E6: 16165 | F6: 8820
A7: Germany | B7: 27690 | C7: 15108 | D7: 12582 | E7: 11550 | F7: 6302
A8: United Kingdom | B8: 18434 | C8: 10060 | D8: 8374 | E8: 15358 | F8: 8380
A9: United States | B9: 116244 | C9: 61205 | D9: 52780 | E9: 55301 | F9: 29036
A10: Grand Total | B10: 329603 | C10: 179640 | D10: 150780 | E10: 152435 | F10: 82569
